{"stats":{"minecraft:crafted":{"minecraft:cooked_chicken":3,"minecraft:oak_button":1,"minecraft:cooked_cod":3,"minecraft:pumpkin_seeds":4},"minecraft:mined":{"minecraft:blue_bed":1},"minecraft:used":{"minecraft:enchanting_table":1,"minecraft:red_sand":4,"minecraft:dead_bush":13,"minecraft:redstone":329,"minecraft:carrot_on_a_stick":5,"minecraft:zombie_villager_spawn_egg":19,"minecraft:ladder":94,"minecraft:oak_sign":34,"minecraft:mycelium":5,"minecraft:spruce_planks":139,"minecraft:zombie_spawn_egg":4,"minecraft:wither_skeleton_spawn_egg":217,"minecraft:quartz_stairs":28,"minecraft:oak_door":2,"minecraft:torch":335,"minecraft:mooshroom_spawn_egg":2,"minecraft:acacia_button":5,"minecraft:blue_concrete":18,"minecraft:stripped_spruce_log":6,"minecraft:polished_diorite":3,"minecraft:birch_door":1,"minecraft:dark_oak_planks":2,"minecraft:lava_bucket":321,"minecraft:bricks":1288,"minecraft:bookshelf":111,"minecraft:villager_spawn_egg":346,"minecraft:jungle_fence_gate":18,"minecraft:grass_block":1223,"minecraft:brick_stairs":36,"minecraft:tropical_fish_spawn_egg":42,"minecraft:dark_oak_slab":13,"minecraft:dark_oak_button":1,"minecraft:stone_brick_stairs":97,"minecraft:slime_spawn_egg":88,"minecraft:magma_cube_spawn_egg":8,"minecraft:birch_button":2,"minecraft:glowstone":251,"minecraft:magma_block":29,"minecraft:redstone_lamp":65,"minecraft:lime_concrete":90,"minecraft:furnace":13,"minecraft:salmon_spawn_egg":3,"minecraft:white_stained_glass_pane":106,"minecraft:podzol":5,"minecraft:minecart":200,"minecraft:trapped_chest":32,"minecraft:egg":257,"minecraft:stone_pressure_plate":30,"minecraft:dark_oak_sapling":23,"minecraft:pumpkin":102,"minecraft:spider_spawn_egg":6,"minecraft:water_bucket":293,"minecraft:zombie_horse_spawn_egg":1,"minecraft:spruce_door":1,"minecraft:birch_planks":9,"minecraft:witch_spawn_egg":6,"minecraft:powered_rail":93,"minecraft:polished_andesite":630,"minecraft:lime_wool":835,"minecraft:oak_planks":69,"minecraft:ender_pearl":2,"minecraft:redstone_block":1,"minecraft:parrot_spawn_egg":31,"minecraft:beacon":7,"minecraft:vindicator_spawn_egg":49,"minecraft:spruce_fence_gate":4,"minecraft:rail":204,"minecraft:tnt":325,"minecraft:crafting_table":30,"minecraft:light_blue_wool":208,"minecraft:squid_spawn_egg":1,"minecraft:cake":8,"minecraft:pumpkin_seeds":39,"minecraft:dark_oak_door":55,"minecraft:creeper_spawn_egg":21,"minecraft:redstone_torch":257,"minecraft:piston":86,"minecraft:ender_eye":126,"minecraft:activator_rail":7,"minecraft:oxeye_daisy":1,"minecraft:acacia_door":1,"minecraft:stone_button":23,"minecraft:detector_rail":42,"minecraft:spruce_trapdoor":35,"minecraft:polished_granite":1580,"minecraft:oak_pressure_plate":1,"minecraft:iron_door":6,"minecraft:ocelot_spawn_egg":6,"minecraft:diamond_sword":41,"minecraft:dark_oak_fence":20,"minecraft:jungle_door":1,"minecraft:white_stained_glass":208,"minecraft:end_portal_frame":164,"minecraft:stripped_oak_log":162,"minecraft:husk_spawn_egg":13,"minecraft:purple_wool":866},"minecraft:killed":{"minecraft:chicken":4,"minecraft:turtle":1,"minecraft:salmon":1,"minecraft:polar_bear":1,"minecraft:villager":3},"minecraft:dropped":{"minecraft:water_bucket":1,"minecraft:iron_ingot":14,"minecraft:vindicator_spawn_egg":1,"minecraft:piston":3,"minecraft:tnt":1,"minecraft:ender_pearl":1,"minecraft:minecart":2,"minecraft:cooked_porkchop":3,"minecraft:bookshelf":1,"minecraft:dark_oak_slab":1,"minecraft:oak_fence":1,"minecraft:grass_block":5,"minecraft:carrot_on_a_stick":1,"minecraft:coal":1,"minecraft:polished_andesite":3,"minecraft:end_rod":1,"minecraft:lava_bucket":2,"minecraft:dark_oak_leaves":1,"minecraft:stone_button":3,"minecraft:torch":2,"minecraft:cooked_cod":1,"minecraft:dead_bush":1,"minecraft:pumpkin":2,"minecraft:purple_wool":1,"minecraft:gold_ingot":9,"minecraft:chorus_plant":1,"minecraft:dark_oak_door":3,"minecraft:bricks":2,"minecraft:cooked_chicken":1,"minecraft:lime_wool":1,"minecraft:oak_planks":3,"minecraft:villager_spawn_egg":3,"minecraft:stripped_oak_log":1,"minecraft:ender_eye":1,"minecraft:oak_sign":1,"minecraft:ocelot_spawn_egg":1,"minecraft:iron_chestplate":1,"minecraft:glowstone":1,"minecraft:ladder":2,"minecraft:redstone_torch":1,"minecraft:white_stained_glass":1,"minecraft:polished_granite":11},"minecraft:custom":{"minecraft:mob_kills":18,"minecraft:interact_with_crafting_table":19,"minecraft:leave_game":49,"minecraft:time_since_death":1381121,"minecraft:climb_one_cm":78507,"minecraft:sprint_one_cm":4261,"minecraft:walk_one_cm":1665007,"minecraft:drop":82,"minecraft:talked_to_villager":14,"minecraft:deaths":2,"minecraft:sneak_time":73044,"minecraft:walk_under_water_one_cm":181719,"minecraft:jump":5294,"minecraft:walk_on_water_one_cm":321640,"minecraft:interact_with_furnace":32,"minecraft:play_one_minute":1818583,"minecraft:sleep_in_bed":36,"minecraft:time_since_rest":237321,"minecraft:open_enderchest":3,"minecraft:damage_taken":560,"minecraft:trigger_trapped_chest":9,"minecraft:minecart_one_cm":1066187,"minecraft:damage_dealt":2858,"minecraft:fly_one_cm":4521613,"minecraft:open_chest":13,"minecraft:crouch_one_cm":40106,"minecraft:horse_one_cm":3454},"minecraft:picked_up":{"minecraft:iron_chestplate":1,"minecraft:purple_wool":2,"minecraft:redstone_block":1,"minecraft:chicken":3,"minecraft:ladder":6,"minecraft:chest_minecart":1,"minecraft:purpur_block":1,"minecraft:golden_sword":1,"minecraft:ocelot_spawn_egg":1,"minecraft:flint_and_steel":1,"minecraft:white_stained_glass":1,"minecraft:blue_orchid":1,"minecraft:oak_sign":3,"minecraft:activator_rail":3,"minecraft:diamond_leggings":1,"minecraft:detector_rail":7,"minecraft:dark_oak_leaves":2,"minecraft:spruce_planks":1,"minecraft:redstone_torch":23,"minecraft:ender_eye":1,"minecraft:poppy":3,"minecraft:minecart":4,"minecraft:sugar_cane":2,"minecraft:chest":1,"minecraft:piston":3,"minecraft:dark_oak_door":3,"minecraft:egg":36,"minecraft:blue_wool":1,"minecraft:lime_wool":1,"minecraft:dark_oak_sapling":1,"minecraft:black_stained_glass":1,"minecraft:stone":1,"minecraft:oak_fence":1,"minecraft:torch":21,"minecraft:villager_spawn_egg":3,"minecraft:stone_button":7,"minecraft:diorite":3,"minecraft:carrot":1,"minecraft:redstone":16,"minecraft:tnt":2,"minecraft:light_blue_wool":1,"minecraft:cooked_cod":1,"minecraft:tropical_fish":11,"minecraft:beetroot_seeds":1,"minecraft:glowstone":1,"minecraft:end_rod":1,"minecraft:bookshelf":1,"minecraft:cobblestone":80,"minecraft:iron_bars":1,"minecraft:rail":9,"minecraft:emerald_ore":1,"minecraft:oxeye_daisy":3,"minecraft:stripped_oak_log":1,"minecraft:furnace_minecart":1,"minecraft:feather":4,"minecraft:iron_door":1,"minecraft:water_bucket":1,"minecraft:andesite":4,"minecraft:salmon":12,"minecraft:leather":4,"minecraft:ice":2,"minecraft:dirt":29,"minecraft:blue_bed":1,"minecraft:polished_granite":13,"minecraft:glass":1,"minecraft:chorus_plant":1,"minecraft:wheat_seeds":26,"minecraft:heart_of_the_sea":1,"minecraft:cooked_chicken":1,"minecraft:glowstone_dust":1,"minecraft:powered_rail":21,"minecraft:oak_planks":3,"minecraft:vindicator_spawn_egg":1,"minecraft:dark_oak_slab":1,"minecraft:cooked_porkchop":3,"minecraft:pumpkin":2,"minecraft:dandelion":6,"minecraft:gravel":2,"minecraft:ink_sac":1,"minecraft:grass_block":5,"minecraft:dead_bush":1,"minecraft:cyan_bed":1,"minecraft:polished_andesite":5,"minecraft:pumpkin_seeds":2,"minecraft:granite":3,"minecraft:oak_sapling":2,"minecraft:chorus_fruit":13,"minecraft:bricks":2,"minecraft:coal":69,"minecraft:purple_concrete_powder":1,"minecraft:ender_pearl":1}},"DataVersion":1976}